README.txt
setup.py
app/__init__.py
pypi_under.egg-info/PKG-INFO
pypi_under.egg-info/SOURCES.txt
pypi_under.egg-info/dependency_links.txt
pypi_under.egg-info/top_level.txt