Metadata-Version: 1.1
Name: pypi-under
Version: 0.0.5
Summary:  Under x Hyphen problem test
Home-page: http://www.usuaro.com
Author: usuario
Author-email: usuario@gmail.com
License: GNU GPLv2
Platform: UNKNOWN
Classifier: Operating System :: OS Independent
Classifier: Programming Language :: Python
